[{"date":"Sun, 22 Sep 2013 03:48:32 GMT","sloc":21,"lloc":7,"functions":2,"deliveredBugs":0.08917553358696377,"maintainability":76.75176589012428,"lintErrors":0,"difficulty":7.619047619047619},{"date":"Sun, 22 Sep 2013 03:49:52 GMT","sloc":21,"lloc":7,"functions":2,"deliveredBugs":0.08917553358696377,"maintainability":76.75176589012428,"lintErrors":0,"difficulty":7.619047619047619},{"date":"Sun, 22 Sep 2013 14:46:27 GMT","sloc":22,"lloc":8,"functions":2,"deliveredBugs":0.1042508118000747,"maintainability":74.79031460004433,"lintErrors":0,"difficulty":7.826086956521739},{"date":"Sun, 22 Sep 2013 14:58:27 GMT","sloc":22,"lloc":8,"functions":2,"deliveredBugs":0.1042508118000747,"maintainability":74.79031460004433,"lintErrors":0,"difficulty":7.826086956521739},{"date":"Sun, 22 Sep 2013 15:00:17 GMT","sloc":22,"lloc":8,"functions":2,"deliveredBugs":0.1042508118000747,"maintainability":74.79031460004433,"lintErrors":0,"difficulty":7.826086956521739},{"date":"Sun, 22 Sep 2013 15:07:07 GMT","sloc":22,"lloc":8,"functions":2,"deliveredBugs":0.1042508118000747,"maintainability":74.79031460004433,"lintErrors":0,"difficulty":7.826086956521739},{"date":"Sun, 22 Sep 2013 15:13:31 GMT","sloc":22,"lloc":8,"functions":2,"deliveredBugs":0.1042508118000747,"maintainability":74.79031460004433,"lintErrors":0,"difficulty":7.826086956521739},{"date":"Sun, 22 Sep 2013 15:14:23 GMT","sloc":22,"lloc":8,"functions":2,"deliveredBugs":0.1042508118000747,"maintainability":74.79031460004433,"lintErrors":0,"difficulty":7.826086956521739},{"date":"Sun, 22 Sep 2013 15:22:33 GMT","sloc":22,"lloc":8,"functions":2,"deliveredBugs":0.1042508118000747,"maintainability":74.79031460004433,"lintErrors":0,"difficulty":7.826086956521739},{"date":"Sun, 22 Sep 2013 15:23:34 GMT","sloc":22,"lloc":8,"functions":2,"deliveredBugs":0.1042508118000747,"maintainability":74.79031460004433,"lintErrors":0,"difficulty":7.826086956521739},{"date":"Sun, 22 Sep 2013 22:42:44 GMT","sloc":22,"lloc":8,"functions":2,"deliveredBugs":0.1042508118000747,"maintainability":74.79031460004433,"lintErrors":0,"difficulty":7.826086956521739},{"date":"Sun, 22 Sep 2013 22:45:00 GMT","sloc":22,"lloc":8,"functions":2,"deliveredBugs":0.1042508118000747,"maintainability":74.79031460004433,"lintErrors":0,"difficulty":7.826086956521739},{"date":"Thu, 26 Sep 2013 19:15:20 GMT","sloc":22,"lloc":8,"functions":2,"deliveredBugs":0.1042508118000747,"maintainability":74.79031460004433,"lintErrors":0,"difficulty":7.826086956521739},{"date":"Fri, 27 Sep 2013 02:01:13 GMT","sloc":22,"lloc":8,"functions":2,"deliveredBugs":0.1042508118000747,"maintainability":74.79031460004433,"lintErrors":0,"difficulty":7.826086956521739}]